pyqt_svg_toolbutton/__init__.py
pyqt_svg_toolbutton/svgToolButton.py
pyqt_svg_toolbutton-0.0.2.dist-info/LICENSE
pyqt_svg_toolbutton-0.0.2.dist-info/METADATA
pyqt_svg_toolbutton-0.0.2.dist-info/WHEEL
pyqt_svg_toolbutton-0.0.2.dist-info/top_level.txt
pyqt_svg_toolbutton-0.0.2.dist-info/RECORD
