Metadata-Version: 2.1
Name: pyqt-svg-toolbutton
Version: 0.0.2
Summary: PyQt SVG icon QToolButton
Home-page: https://github.com/yjg30737/pyqt-svg-toolbutton.git
Author: Jung Gyu Yoon
Author-email: yjg30737@gmail.com
License: MIT
Platform: UNKNOWN
License-File: LICENSE
Requires-Dist: PyQt5 (>=5.8)
Requires-Dist: pyqt-svg-abstractbutton (>=0.0.1)
